dataclass_serializer/__init__.py
dataclass_serializer/dataclass_serializer.py
dataclass_serializer-1.3.2.dist-info/METADATA
dataclass_serializer-1.3.2.dist-info/WHEEL
dataclass_serializer-1.3.2.dist-info/top_level.txt
dataclass_serializer-1.3.2.dist-info/RECORD
